{
  "first_name": "Sarah",
  "last_name": "Johnson",
  "bio": "I'm a software engineer with 8 years of experience in web development. I enjoy building user-friendly applications and working with modern technologies like React and TypeScript. In my free time, I love hiking, reading tech blogs, and contributing to open source projects.",
  "dob": "1990-05-15",
  "gender": "female",
  "marital_status": "married",
  "spouse_name": "Michael Johnson",
  "email": "sarah.johnson@example.com",
  "phone": "+1234567890",
  "country": "us",
  "state": "ca",
  "address_line1": "123 Main Street",
  "address_line2": "Apt 4B",
  "city": "San Francisco",
  "zip": "94102",
  "username": "sarah_johnson",
  "password": "SecurePass123",
  "confirm_password": "SecurePass123",
  "newsletter": true,
  "user_role": "editor"
}
